decorators/__init__.py
decorators/timing.py
timing/__init__.py
timing/timing.py
time_stuff-0.0.3.dist-info/METADATA
time_stuff-0.0.3.dist-info/WHEEL
time_stuff-0.0.3.dist-info/top_level.txt
time_stuff-0.0.3.dist-info/RECORD
