Metadata-Version: 2.1
Name: time-stuff
Version: 0.0.3
Summary: For tracking time
Home-page: UNKNOWN
Author: Hayo Ottens
Author-email: <hayo.ottens@gmail.com>
License: UNKNOWN
Keywords: python,time,time tracking
Platform: UNKNOWN
Classifier: Development Status :: 3 - Alpha
Classifier: Intended Audience :: Education
Classifier: Programming Language :: Python :: 2
Classifier: Programming Language :: Python :: 3
Classifier: Operating System :: MacOS :: MacOS X
Classifier: Operating System :: Microsoft :: Windows
